a2rl/__init__.py
a2rl/_dataframe.py
a2rl/_io.py
a2rl/_metadatadict.py
a2rl/config.yaml
a2rl/nbtools.py
a2rl/py.typed
a2rl/simulator.py
a2rl/tokenizer.py
a2rl/utils.py
a2rl/dataset/__init__.py
a2rl/dataset/chiller/data.csv
a2rl/dataset/chiller/metadata.yaml
a2rl/dataset/rtu/data.csv
a2rl/dataset/rtu/metadata.yaml
a2rl/experimental/__init__.py
a2rl/experimental/lightgpt/__init__.py
a2rl/experimental/lightgpt/config.yaml
a2rl/experimental/lightgpt/lr_decay.py
a2rl/experimental/lightgpt/model.py
a2rl/experimental/lightgpt/simulator.py
a2rl/mingpt/__init__.py
a2rl/mingpt/model.py
a2rl/mingpt/trainer.py
a2rl-1.2.0.dist-info/LICENSE
a2rl-1.2.0.dist-info/METADATA
a2rl-1.2.0.dist-info/NOTICE
a2rl-1.2.0.dist-info/WHEEL
a2rl-1.2.0.dist-info/top_level.txt
a2rl-1.2.0.dist-info/RECORD
