Metadata-Version: 2.1
Name: a2rl
Version: 1.2.0
Summary: Make recommendations for sequential decision problems using offline data
Home-page: https://github.com/awslabs/amazon-accessible-rl-sdk/
Download-URL: 
Author: AWS/ProServe Global Team
License: Apache License 2.0
Project-URL: Bug Tracker, https://github.com/awslabs/amazon-accessible-rl-sdk/issues/
Project-URL: Documentation, https://amazon-accessible-rl-sdk.readthedocs.io/en/stable/
Project-URL: Source Code, https://github.com/awslabs/amazon-accessible-rl-sdk/
Platform: any
Classifier: Programming Language :: Python :: 3.8
Classifier: Programming Language :: Python :: 3.9
Classifier: Programming Language :: Python :: 3.10
Requires-Python: >=3.8.0
License-File: LICENSE
License-File: NOTICE
Requires-Dist: pandas
Requires-Dist: numpy
Requires-Dist: scikit-learn
Requires-Dist: scipy
Requires-Dist: matplotlib
Requires-Dist: torch
Requires-Dist: tqdm (>=4.64.1)
Requires-Dist: PyYaml (>=5.1)
Requires-Dist: typing-extensions
Requires-Dist: typeguard (>=3.0.0)
Requires-Dist: nptyping
Requires-Dist: loguru
Requires-Dist: gym (<0.26.0,>=0.23.1)
Requires-Dist: seaborn
Requires-Dist: cloudpickle
Requires-Dist: pytorch-lightning (>=1.5.0)
Requires-Dist: tensorboardX
Provides-Extra: dev
Requires-Dist: ipykernel ; extra == 'dev'
Requires-Dist: pre-commit ; extra == 'dev'
Requires-Dist: black ; extra == 'dev'
Requires-Dist: isort ; extra == 'dev'
Requires-Dist: mypy ; extra == 'dev'
Requires-Dist: autoflake ; extra == 'dev'
Requires-Dist: flake8 ; extra == 'dev'
Requires-Dist: types-PyYAML ; extra == 'dev'
Requires-Dist: types-tqdm ; extra == 'dev'
Requires-Dist: types-setuptools ; extra == 'dev'
Requires-Dist: ipdb ; extra == 'dev'
Requires-Dist: ipywidgets ; extra == 'dev'
Requires-Dist: rich ; extra == 'dev'
Requires-Dist: sphinx-autobuild ; extra == 'dev'
Requires-Dist: bump2version ; extra == 'dev'
Provides-Extra: test
Requires-Dist: pytest ; extra == 'test'
Requires-Dist: pytest-cov ; extra == 'test'
Requires-Dist: pytest-sphinx ; extra == 'test'
Requires-Dist: safety ; extra == 'test'
Requires-Dist: pytest-lazy-fixture ; extra == 'test'
Requires-Dist: pytest-console-scripts ; extra == 'test'
Requires-Dist: pytest-xdist ; extra == 'test'
